new_library_package/__init__.py
new_library_package/dummy_file.py
new_library_package-3.0.1.dist-info/LICENSE
new_library_package-3.0.1.dist-info/METADATA
new_library_package-3.0.1.dist-info/WHEEL
new_library_package-3.0.1.dist-info/top_level.txt
new_library_package-3.0.1.dist-info/RECORD
