Metadata-Version: 2.1
Name: new-library-package
Version: 3.0.1
Summary: Demo for release package
Home-page: https://github.com/Hi-dlwlrma/demo-package
Author-email: dungntn@gmail.com
Classifier: Programming Language :: Python :: 3
Classifier: License :: OSI Approved :: MIT License
Classifier: Intended Audience :: Developers
Classifier: Operating System :: OS Independent
Requires-Python: >=3.8
License-File: LICENSE
